.gitignore
README.md
a.py
ode.md
setup.py
DFPy.egg-info/PKG-INFO
DFPy.egg-info/SOURCES.txt
DFPy.egg-info/dependency_links.txt
DFPy.egg-info/requires.txt
DFPy.egg-info/top_level.txt
dfpy/__init__.py
dfpy/diff_eq.py
dfpy/profile.py
dfpy/state.py
dfpy/backend/__init__.py
dfpy/backend/_numpy_gpu.py
dfpy/backend/generate_overloads.py
dfpy/backend/numba_overloads.py
dfpy/dde/__init__.py
dfpy/delay_fde/__init__.py
dfpy/delay_fde/abm_methods.py
dfpy/fde/__init__.py
dfpy/ode/__init__.py
dfpy/ode/adaptive_methods.py
dfpy/ode/implicit_methods.py
dfpy/ode/other_methods.py
dfpy/ode/runge_kutta_methods.py
dfpy/ode/tests.py
dfpy/sde/__init__.py
dfpy/sde/other_methods.py
dfpy/sde/srk_scalar.py
dfpy/sde/srk_strong.py
dfpy/sde/srk_weak.py
docs/Makefile
docs/conf.py
docs/index.rst
docs/make.bat
docs/apis/integration.rst